[
    {
        "context": "Protokol internet adalah seperangkat aturan yang mengatur komunikasi data melalui internet.  TCP/IP adalah protokol internet yang paling umum digunakan. TCP (Transmission Control Protocol) memastikan pengiriman data yang andal, sedangkan IP (Internet Protocol) menangani pengalamatan dan routing data. HTTP (Hypertext Transfer Protocol) digunakan untuk mengakses situs web.  HTTPS adalah versi HTTP yang aman yang mengenkripsi data untuk melindungi informasi sensitif.  DNS (Domain Name System) menerjemahkan nama domain yang mudah diingat (seperti google.com) ke alamat IP numerik yang digunakan oleh komputer.  Firewall adalah sistem keamanan yang memantau dan mengontrol lalu lintas jaringan masuk dan keluar berdasarkan aturan keamanan yang telah ditentukan.  VPN (Virtual Private Network) membuat koneksi aman melalui jaringan publik, seperti internet.Server web adalah komputer yang menyimpan dan mengirimkan situs web.  Mereka menjalankan perangkat lunak server web, seperti Apache atau Nginx, yang menangani permintaan HTTP dari browser web.  Server web dapat menangani banyak permintaan secara bersamaan.  Load balancing mendistribusikan lalu lintas jaringan di beberapa server untuk meningkatkan kinerja dan ketersediaan.  Cloud computing menyediakan sumber daya komputasi, seperti server, penyimpanan, dan perangkat lunak, melalui internet.  CDN (Content Delivery Network) adalah jaringan server yang terdistribusi secara geografis yang mengirimkan konten web, seperti video dan gambar, ke pengguna berdasarkan lokasi mereka. Server web adalah jantung dari internet, memungkinkan kita untuk mengakses informasi dari seluruh dunia. Mereka bekerja tanpa lelah di balik layar, memproses jutaan permintaan setiap hari.  Keamanan server web sangat penting untuk melindungi data sensitif dari akses yang tidak sah.  Protokol keamanan, seperti HTTPS dan SSL, mengenkripsi data yang ditransmisikan antara browser web dan server web.Internet of Things (IoT) menghubungkan perangkat sehari-hari ke internet, memungkinkan mereka untuk mengumpulkan dan bertukar data.  Smart home menggunakan perangkat IoT untuk mengotomatiskan tugas, seperti mengontrol pencahayaan dan suhu.  5G adalah standar jaringan seluler generasi kelima yang menawarkan kecepatan data yang lebih tinggi dan latensi yang lebih rendah.  Keamanan IoT adalah masalah penting, karena perangkat IoT yang terhubung dapat rentan terhadap serangan siber.  Data mining adalah proses mengekstrak pengetahuan yang berguna dari data dalam jumlah besar.  Big data mengacu pada kumpulan data yang terlalu besar dan kompleks untuk diproses oleh metode tradisional.  Kecerdasan buatan (AI) menggunakan algoritma untuk meniru kecerdasan manusia.Server adalah tulang punggung dari banyak layanan online yang kita gunakan setiap hari, mulai dari media sosial hingga perbankan online.  Mereka menyimpan data kita, memproses transaksi kita, dan menghubungkan kita dengan orang lain di seluruh dunia.  Ketika Anda mengakses situs web, browser web Anda mengirimkan permintaan HTTP ke server web, yang kemudian mengirimkan kembali file-file yang diperlukan untuk menampilkan halaman web tersebut.  Proses ini terjadi dalam hitungan detik, memungkinkan kita untuk mengakses informasi dengan cepat dan efisien.  Internet telah merevolusi cara kita berkomunikasi, bekerja, dan mengakses informasi.  Ini telah menghubungkan dunia dengan cara yang belum pernah terjadi sebelumnya, memungkinkan kita untuk berbagi ide, belajar, dan berkolaborasi dengan orang lain di seluruh dunia.  HTTP adalah protokol tanpa status, yang berarti setiap permintaan diperlakukan secara independen.  Cookie digunakan untuk menyimpan informasi tentang sesi pengguna, seperti item di keranjang belanja online.Jaringan komputer memungkinkan kita untuk berbagi sumber daya, seperti printer dan file, dan untuk berkomunikasi satu sama lain melalui email, pesan instan, dan video conference.  Topologi jaringan menggambarkan tata letak fisik atau logis dari jaringan.  Topologi umum termasuk bus, bintang, ring, dan mesh.  Ethernet adalah teknologi jaringan area lokal (LAN) yang paling umum digunakan.  Wi-Fi memungkinkan perangkat untuk terhubung ke jaringan tanpa kabel.  Switch jaringan menghubungkan beberapa perangkat di LAN, sedangkan router menghubungkan LAN ke internet.  Keamanan jaringan sangat penting untuk melindungi data sensitif dari akses yang tidak sah.  Firewall, sistem deteksi intrusi, dan perangkat lunak antivirus adalah komponen penting dari keamanan jaringan.  OSI model adalah kerangka kerja konseptual yang menstandardisasi komunikasi antar sistem komputer.  Ini terdiri dari tujuh lapisan: fisik, tautan data, jaringan, transport, sesi, presentasi, dan aplikasi. Setiap lapisan memiliki fungsi tertentu dalam proses komunikasi.Jaringan komputer telah mengubah cara kita bekerja, berkomunikasi, dan mengakses informasi.  Mereka memungkinkan kita untuk berkolaborasi dalam proyek, berbagi ide, dan terhubung dengan orang lain di seluruh dunia.  Dari email hingga media sosial hingga cloud computing, jaringan komputer telah menjadi bagian integral dari kehidupan kita sehari-hari.  Mereka telah memungkinkan kita untuk bekerja dari jarak jauh, belajar online, dan mengakses informasi dari mana saja di dunia.",
        "questions": {
            "questions": [
                {
                    "id": 1,
                    "type": "multiple_choice",
                    "question": "Apa kepanjangan dari TCP/IP?",
                    "options": [
                        {
                            "id": "a",
                            "text": "Transmission Control Protocol/Internet Protocol"
                        },
                        {
                            "id": "b",
                            "text": "Transfer Control Protocol/Internet Protocol"
                        },
                        {
                            "id": "c",
                            "text": "Transmission Control Protocol/Intranet Protocol"
                        },
                        {
                            "id": "d",
                            "text": "Transfer Control Protocol/Intranet Protocol"
                        }
                    ],
                    "correct_answer": "a",
                    "explanation": "TCP/IP adalah singkatan dari Transmission Control Protocol/Internet Protocol."
                },
                {
                    "id": 2,
                    "type": "true_false",
                    "question": "HTTP adalah protokol yang aman untuk transfer data sensitif.",
                    "correct_answer": false,
                    "explanation": "HTTPS adalah versi HTTP yang aman, bukan HTTP itu sendiri."
                },
                {
                    "id": 3,
                    "type": "multiple_choice",
                    "question": "Apa fungsi DNS?",
                    "options": [
                        {
                            "id": "a",
                            "text": "Mengirim email"
                        },
                        {
                            "id": "b",
                            "text": "Menerjemahkan nama domain ke alamat IP"
                        },
                        {
                            "id": "c",
                            "text": "Mengenkripsi data"
                        },
                        {
                            "id": "d",
                            "text": "Membuat koneksi aman"
                        }
                    ],
                    "correct_answer": "b",
                    "explanation": "DNS menerjemahkan nama domain yang mudah diingat ke alamat IP numerik."
                },
                {
                    "id": 4,
                    "type": "multibox",
                    "question": "Manakah yang termasuk dalam topologi jaringan?",
                    "options": [
                        {
                            "id": "a",
                            "text": "Bus"
                        },
                        {
                            "id": "b",
                            "text": "Star"
                        },
                        {
                            "id": "c",
                            "text": "HTTP"
                        },
                        {
                            "id": "d",
                            "text": "Ring"
                        }
                    ],
                    "correct_answer": [
                        "a",
                        "b",
                        "d"
                    ],
                    "explanation": "Bus, Star, dan Ring adalah topologi jaringan. HTTP adalah protokol, bukan topologi."
                },
                {
                    "id": 5,
                    "type": "multiple_choice",
                    "question": "Apa fungsi load balancing pada server?",
                    "options": [
                        {
                            "id": "a",
                            "text": "Menyimpan data"
                        },
                        {
                            "id": "b",
                            "text": "Mendistribusikan lalu lintas jaringan"
                        },
                        {
                            "id": "c",
                            "text": "Menerjemahkan nama domain"
                        },
                        {
                            "id": "d",
                            "text": "Mengenali virus"
                        }
                    ],
                    "correct_answer": "b",
                    "explanation": "Load balancing mendistribusikan lalu lintas jaringan di beberapa server."
                }
            ]
        }
    },
    {
        "context": "Jaringan komputer adalah kumpulan komputer dan perangkat lain yang terhubung satu sama lain untuk berbagi sumber daya dan informasi. Jaringan ini dapat berkisar dari jaringan rumah kecil yang menghubungkan beberapa komputer dan printer hingga internet global yang menghubungkan miliaran perangkat.  Jaringan komputer memungkinkan kita untuk berbagi file, mengakses internet, mengirim email, dan berkomunikasi satu sama lain secara real time. Ada berbagai jenis jaringan komputer, masing-masing dengan karakteristik dan kegunaannya sendiri.  LAN (Local Area Network) adalah jaringan yang terbatas pada area geografis yang kecil, seperti rumah, kantor, atau sekolah.  WAN (Wide Area Network) adalah jaringan yang mencakup area geografis yang luas, seperti negara atau benua.  Internet adalah contoh WAN terbesar.  MAN (Metropolitan Area Network) adalah jaringan yang mencakup kota atau wilayah metropolitan.  Jaringan komputer menggunakan berbagai protokol, yaitu seperangkat aturan yang mengatur komunikasi data, untuk memastikan bahwa data ditransmisikan dengan benar.  TCP/IP adalah protokol yang paling umum digunakan di internet.  Protokol lain termasuk HTTP, FTP, dan SMTP.  Topologi jaringan menggambarkan tata letak fisik atau logis dari jaringan.  Topologi umum termasuk bus, bintang, ring, dan mesh.  Setiap topologi memiliki kelebihan dan kekurangannya sendiri dalam hal kinerja, keandalan, dan biaya. Keamanan jaringan sangat penting untuk melindungi data sensitif dari akses yang tidak sah.  Firewall, sistem deteksi intrusi, dan perangkat lunak antivirus adalah komponen penting dari keamanan jaringan.  Praktik keamanan yang baik, seperti kata sandi yang kuat dan pembaruan perangkat lunak secara teratur, juga penting untuk menjaga keamanan jaringan.  Jaringan nirkabel, seperti Wi-Fi, telah menjadi semakin populer dalam beberapa tahun terakhir.  Wi-Fi memungkinkan perangkat untuk terhubung ke jaringan tanpa kabel, memberikan fleksibilitas dan mobilitas yang lebih besar.  Namun, jaringan nirkabel juga dapat lebih rentan terhadap serangan siber jika tidak diamankan dengan benar. Cloud computing adalah model untuk memungkinkan akses jaringan yang nyaman sesuai permintaan ke kumpulan sumber daya komputasi bersama yang dapat dikonfigurasi (misalnya, jaringan, server, penyimpanan, aplikasi, dan layanan) yang dapat dengan cepat disediakan dan dirilis dengan upaya manajemen minimal atau interaksi penyedia layanan. Cloud computing telah merevolusi cara bisnis dan individu menggunakan teknologi.  Ini menyediakan akses ke sumber daya komputasi yang kuat tanpa perlu investasi perangkat keras dan perangkat lunak yang besar.  Layanan cloud umum termasuk penyimpanan data, perangkat lunak sebagai layanan (SaaS), dan platform sebagai layanan (PaaS).  Jaringan komputer telah mengubah cara kita hidup, bekerja, dan berkomunikasi.  Mereka telah menghubungkan dunia dengan cara yang belum pernah terjadi sebelumnya, memungkinkan kita untuk berbagi informasi, berkolaborasi dalam proyek, dan terhubung dengan orang lain di seluruh dunia.  Dengan terus berkembangnya teknologi, jaringan komputer akan terus memainkan peran yang semakin penting dalam kehidupan kita. Server web adalah program komputer yang mendistribusikan halaman web sesuai permintaan. Ketika klien, biasanya browser web atau perayap web, mengirimkan permintaan untuk halaman web yang terletak di server web, server merespons dengan mengirimkan file yang diminta ke klien yang membuat halaman web yang diminta tersedia untuk dilihat. Server web memungkinkan pengguna di seluruh dunia untuk mengakses situs web melalui internet. Mereka bertanggung jawab untuk menyimpan, memproses, dan mengirimkan halaman web ke pengguna akhir.  Server web menjalankan perangkat lunak khusus yang memungkinkan mereka untuk berkomunikasi dengan browser web dan mengirimkan konten web yang diminta.  Ketika Anda mengetikkan alamat web di browser Anda, browser Anda mengirimkan permintaan ke server web yang menghosting situs web tersebut.  Server web kemudian memproses permintaan tersebut dan mengirimkan kembali file-file yang diperlukan untuk menampilkan situs web tersebut di browser Anda.  Proses ini terjadi dalam hitungan detik, memungkinkan Anda untuk mengakses informasi dari seluruh dunia dengan cepat dan efisien. HTTP (Hypertext Transfer Protocol) adalah protokol yang digunakan untuk mentransfer data melalui World Wide Web.  Ketika Anda mengakses situs web, browser Anda mengirimkan permintaan HTTP ke server web, yang kemudian mengirimkan kembali halaman web yang diminta.  HTTPS (Hypertext Transfer Protocol Secure) adalah versi HTTP yang aman yang mengenkripsi komunikasi antara browser Anda dan server web, melindungi informasi sensitif dari akses yang tidak sah.",
        "questions": {
            "questions": [
                {
                    "id": 1,
                    "type": "multiple_choice",
                    "question": "Apa yang dimaksud dengan LAN?",
                    "options": [
                        {
                            "id": "a",
                            "text": "Local Area Network"
                        },
                        {
                            "id": "b",
                            "text": "Large Area Network"
                        },
                        {
                            "id": "c",
                            "text": "Long Area Network"
                        },
                        {
                            "id": "d",
                            "text": "Lost Area Network"
                        }
                    ],
                    "correct_answer": "a",
                    "explanation": "LAN singkatan dari Local Area Network."
                },
                {
                    "id": 2,
                    "type": "true_false",
                    "question": "Internet adalah contoh dari MAN.",
                    "correct_answer": false,
                    "explanation": "Internet adalah contoh dari WAN (Wide Area Network)."
                },
                {
                    "id": 3,
                    "type": "multiple_choice",
                    "question": "Protokol apa yang paling umum digunakan di internet?",
                    "options": [
                        {
                            "id": "a",
                            "text": "HTTP"
                        },
                        {
                            "id": "b",
                            "text": "FTP"
                        },
                        {
                            "id": "c",
                            "text": "SMTP"
                        },
                        {
                            "id": "d",
                            "text": "TCP/IP"
                        }
                    ],
                    "correct_answer": "d",
                    "explanation": "TCP/IP adalah protokol yang paling umum digunakan di internet."
                },
                {
                    "id": 4,
                    "type": "multibox",
                    "question": "Apa saja komponen penting keamanan jaringan?",
                    "options": [
                        {
                            "id": "a",
                            "text": "Firewall"
                        },
                        {
                            "id": "b",
                            "text": "Sistem deteksi intrusi"
                        },
                        {
                            "id": "c",
                            "text": "Perangkat lunak antivirus"
                        },
                        {
                            "id": "d",
                            "text": "Kata sandi yang lemah"
                        }
                    ],
                    "correct_answer": [
                        "a",
                        "b",
                        "c"
                    ],
                    "explanation": "Firewall, sistem deteksi intrusi, dan perangkat lunak antivirus penting untuk keamanan jaringan. Kata sandi yang lemah justru membahayakan keamanan."
                },
                {
                    "id": 5,
                    "type": "multiple_choice",
                    "question": "Apa yang dimaksud dengan cloud computing?",
                    "options": [
                        {
                            "id": "a",
                            "text": "Jaringan komputer lokal"
                        },
                        {
                            "id": "b",
                            "text": "Akses jaringan ke sumber daya komputasi bersama"
                        },
                        {
                            "id": "c",
                            "text": "Perangkat keras untuk menyimpan data"
                        },
                        {
                            "id": "d",
                            "text": "Perangkat lunak untuk mengakses internet"
                        }
                    ],
                    "correct_answer": "b",
                    "explanation": "Cloud computing menyediakan akses sesuai permintaan ke sumber daya komputasi bersama."
                }
            ]
        }
    },
    {
        "context": "Internet, jaringan global yang menghubungkan miliaran komputer dan perangkat, telah merevolusi cara kita berkomunikasi, bekerja, dan mengakses informasi.  Internet memungkinkan kita untuk mengirim email, menjelajahi web, melakukan streaming video, dan terhubung dengan orang lain di seluruh dunia secara real time.  Internet menggunakan serangkaian protokol, yaitu seperangkat aturan yang mengatur komunikasi data, untuk memastikan bahwa data ditransmisikan dengan benar antara perangkat.  Protokol inti internet adalah TCP/IP (Transmission Control Protocol/Internet Protocol).  TCP memastikan pengiriman data yang andal, sedangkan IP menangani pengalamatan dan perutean data.  Protokol lain yang umum digunakan di internet termasuk HTTP (Hypertext Transfer Protocol) untuk mengakses situs web, FTP (File Transfer Protocol) untuk mentransfer file, dan SMTP (Simple Mail Transfer Protocol) untuk mengirim email. Arsitektur internet didesain untuk desentralisasi dan redundansi, yang berarti tidak ada satu titik kegagalan pun.  Jika satu bagian dari internet gagal, data dapat dialihkan melalui jalur alternatif.  Desain ini membuat internet sangat tangguh dan tahan terhadap gangguan.  World Wide Web (WWW) seringkali keliru dianggap sama dengan internet, tetapi sebenarnya WWW hanyalah salah satu layanan yang berjalan di atas internet.  WWW adalah sistem dokumen hiperteks yang saling terhubung yang diakses melalui internet.  Situs web dihosting di server web dan diakses menggunakan browser web, seperti Chrome, Firefox, atau Safari.  Perkembangan teknologi web, seperti HTML5, CSS3, dan JavaScript, telah memungkinkan pembuatan situs web yang interaktif dan dinamis. Keamanan siber menjadi semakin penting karena semakin banyak kehidupan kita yang bergantung pada internet.  Serangan siber, seperti malware, phishing, dan denial-of-service attack, dapat menyebabkan kerusakan yang signifikan pada individu dan organisasi.  Penting untuk mengambil langkah-langkah untuk melindungi diri dari serangan siber, seperti menggunakan kata sandi yang kuat, memperbarui perangkat lunak secara teratur, dan berhati-hati terhadap email dan tautan yang mencurigakan.  Jaringan komputer, yang membentuk dasar dari internet, memungkinkan komputer dan perangkat lain untuk berbagi sumber daya dan informasi.  Jaringan dapat berkisar dari jaringan rumah kecil yang menghubungkan beberapa komputer dan printer hingga jaringan perusahaan besar yang menghubungkan ribuan pengguna.  Jaringan komputer menggunakan berbagai topologi, yaitu tata letak fisik atau logis dari jaringan.  Topologi umum termasuk bus, bintang, ring, dan mesh.  Setiap topologi memiliki kelebihan dan kekurangannya sendiri dalam hal kinerja, keandalan, dan biaya. Server web adalah komputer yang menyimpan dan mengirimkan situs web.  Mereka menjalankan perangkat lunak server web, seperti Apache atau Nginx, yang menangani permintaan HTTP dari browser web.  Server web dapat menangani banyak permintaan secara bersamaan, memungkinkan jutaan pengguna untuk mengakses situs web setiap hari.  Ketika Anda mengetikkan alamat web di browser Anda, browser Anda mengirimkan permintaan HTTP ke server web yang menghosting situs web tersebut.  Server web kemudian memproses permintaan tersebut dan mengirimkan kembali file-file yang diperlukan untuk menampilkan situs web tersebut di browser Anda. Proses ini terjadi dalam hitungan detik, memungkinkan Anda untuk mengakses informasi dari seluruh dunia dengan cepat dan efisien.   Keamanan server web sangat penting untuk melindungi data sensitif dari akses yang tidak sah.  Protokol keamanan, seperti HTTPS dan SSL, mengenkripsi data yang ditransmisikan antara browser web dan server web. Teknologi cloud computing memungkinkan individu dan organisasi untuk mengakses sumber daya komputasi, seperti server, penyimpanan, dan perangkat lunak, melalui internet.  Cloud computing menawarkan skalabilitas, fleksibilitas, dan penghematan biaya dibandingkan dengan solusi hosting tradisional.  Layanan cloud umum termasuk penyimpanan data, perangkat lunak sebagai layanan (SaaS), dan platform sebagai layanan (PaaS).  Internet of Things (IoT) mengacu pada jaringan perangkat fisik yang terhubung ke internet, yang dapat mengumpulkan dan bertukar data.  Perangkat IoT berkisar dari peralatan rumah tangga pintar hingga sensor industri.  IoT memiliki potensi untuk merevolusi berbagai industri, mulai dari perawatan kesehatan hingga manufaktur.  Keamanan IoT merupakan pertimbangan penting, karena perangkat IoT yang terhubung dapat rentan terhadap serangan siber.",
        "questions": {
            "questions": [
                {
                    "id": 1,
                    "type": "multiple_choice",
                    "question": "Apa protokol inti internet?",
                    "options": [
                        {
                            "id": "a",
                            "text": "HTTP"
                        },
                        {
                            "id": "b",
                            "text": "FTP"
                        },
                        {
                            "id": "c",
                            "text": "TCP/IP"
                        },
                        {
                            "id": "d",
                            "text": "SMTP"
                        }
                    ],
                    "correct_answer": "c",
                    "explanation": "TCP/IP adalah protokol inti internet."
                },
                {
                    "id": 2,
                    "type": "true_false",
                    "question": "World Wide Web (WWW) sama dengan internet.",
                    "correct_answer": false,
                    "explanation": "WWW adalah layanan yang berjalan di atas internet, bukan internet itu sendiri."
                },
                {
                    "id": 3,
                    "type": "multiple_choice",
                    "question": "Apa fungsi server web?",
                    "options": [
                        {
                            "id": "a",
                            "text": "Mengirim email"
                        },
                        {
                            "id": "b",
                            "text": "Menyimpan dan mengirimkan situs web"
                        },
                        {
                            "id": "c",
                            "text": "Menerjemahkan nama domain"
                        },
                        {
                            "id": "d",
                            "text": "Mengenkripsi data"
                        }
                    ],
                    "correct_answer": "b",
                    "explanation": "Server web menyimpan dan mengirimkan situs web."
                },
                {
                    "id": 4,
                    "type": "multibox",
                    "question": "Manakah yang termasuk dalam contoh serangan siber?",
                    "options": [
                        {
                            "id": "a",
                            "text": "Malware"
                        },
                        {
                            "id": "b",
                            "text": "Phishing"
                        },
                        {
                            "id": "c",
                            "text": "Firewall"
                        },
                        {
                            "id": "d",
                            "text": "Denial-of-service attack"
                        }
                    ],
                    "correct_answer": [
                        "a",
                        "b",
                        "d"
                    ],
                    "explanation": "Malware, phishing, dan denial-of-service attack adalah contoh serangan siber. Firewall adalah sistem pertahanan."
                },
                {
                    "id": 5,
                    "type": "multiple_choice",
                    "question": "Apa yang dimaksud dengan IoT?",
                    "options": [
                        {
                            "id": "a",
                            "text": "Jaringan perangkat fisik yang terhubung ke internet"
                        },
                        {
                            "id": "b",
                            "text": "Perangkat lunak untuk mengakses internet"
                        },
                        {
                            "id": "c",
                            "text": "Protokol untuk mengirim email"
                        },
                        {
                            "id": "d",
                            "text": "Topologi jaringan"
                        }
                    ],
                    "correct_answer": "a",
                    "explanation": "IoT (Internet of Things) adalah jaringan perangkat fisik yang terhubung ke internet."
                }
            ]
        }
    },
    {
        "context": "Jaringan komputer memungkinkan berbagai perangkat, seperti komputer, ponsel, dan printer, untuk terhubung dan berbagi informasi satu sama lain.  Jaringan dapat berkisar dari jaringan rumah kecil hingga internet global yang luas.  Ada berbagai jenis jaringan, termasuk LAN (Local Area Network), WAN (Wide Area Network), dan MAN (Metropolitan Area Network).  Setiap jenis jaringan memiliki karakteristik dan kegunaannya sendiri. Protokol jaringan adalah seperangkat aturan yang mengatur komunikasi data antara perangkat di jaringan.  TCP/IP (Transmission Control Protocol/Internet Protocol) adalah protokol yang paling umum digunakan di internet.  Protokol lain termasuk HTTP (Hypertext Transfer Protocol) untuk mengakses situs web, FTP (File Transfer Protocol) untuk mentransfer file, dan SMTP (Simple Mail Transfer Protocol) untuk mengirim email.  Model OSI (Open Systems Interconnection) adalah kerangka kerja konseptual yang menstandardisasi komunikasi antar sistem komputer.  Model ini terdiri dari tujuh lapisan, masing-masing dengan fungsi tertentu dalam proses komunikasi. Keamanan jaringan sangat penting untuk melindungi data sensitif dari akses yang tidak sah.  Firewall, sistem deteksi intrusi, dan perangkat lunak antivirus adalah komponen penting dari keamanan jaringan.  Praktik keamanan yang baik, seperti kata sandi yang kuat dan pembaruan perangkat lunak secara teratur, juga penting untuk menjaga keamanan jaringan.  Kriptografi digunakan untuk mengamankan komunikasi dengan mengenkripsi data, membuatnya tidak dapat dibaca oleh pihak yang tidak berwenang.  Algoritma kriptografi, seperti AES dan RSA, digunakan untuk mengenkripsi dan mendekripsi data.  VPN (Virtual Private Network) membuat koneksi aman melalui jaringan publik, seperti internet, memungkinkan pengguna untuk mengakses sumber daya jaringan dengan aman dari lokasi terpencil. Cloud computing menyediakan akses sesuai permintaan ke sumber daya komputasi bersama, seperti server, penyimpanan, dan perangkat lunak, melalui internet.  Layanan cloud umum termasuk penyimpanan data, perangkat lunak sebagai layanan (SaaS), dan platform sebagai layanan (PaaS).  Cloud computing menawarkan skalabilitas, fleksibilitas, dan penghematan biaya dibandingkan dengan solusi hosting tradisional.  Edge computing memproses data lebih dekat ke sumbernya, mengurangi latensi dan bandwidth yang dibutuhkan.  IoT (Internet of Things) menghubungkan perangkat sehari-hari ke internet, memungkinkan mereka untuk mengumpulkan dan bertukar data.  Smart home, kendaraan yang terhubung, dan perangkat yang dapat dikenakan adalah contoh aplikasi IoT.  Keamanan IoT merupakan pertimbangan penting, karena perangkat IoT yang terhubung dapat rentan terhadap serangan siber.Server web adalah komputer yang menyimpan dan mengirimkan situs web.  Mereka menjalankan perangkat lunak server web, seperti Apache atau Nginx, yang menangani permintaan HTTP dari browser web.  Server web dapat menangani banyak permintaan secara bersamaan.  Load balancing mendistribusikan lalu lintas jaringan di beberapa server untuk meningkatkan kinerja dan ketersediaan. DNS (Domain Name System) menerjemahkan nama domain yang mudah diingat (seperti google.com) ke alamat IP numerik yang digunakan oleh komputer.  HTTP (Hypertext Transfer Protocol) adalah protokol yang digunakan untuk mengakses situs web.  HTTPS adalah versi HTTP yang aman yang mengenkripsi data untuk melindungi informasi sensitif.   Arsitektur client-server adalah model komputasi terdistribusi di mana server menyediakan layanan ke beberapa klien.  Klien mengirimkan permintaan ke server, dan server merespons dengan memberikan layanan yang diminta.  Web browser adalah contoh aplikasi klien yang digunakan untuk mengakses situs web yang dihosting di server web. Teknologi 5G menawarkan kecepatan data yang jauh lebih tinggi dan latensi yang lebih rendah dibandingkan dengan generasi jaringan seluler sebelumnya.  5G memungkinkan aplikasi baru, seperti augmented reality dan virtual reality, dan mendukung pertumbuhan IoT.  Kecerdasan buatan (AI) dan machine learning (ML) digunakan dalam jaringan komputer untuk mengotomatiskan tugas, meningkatkan kinerja, dan meningkatkan keamanan.  AI dan ML dapat digunakan untuk mendeteksi anomali, memprediksi kegagalan, dan mengoptimalkan lalu lintas jaringan.",
        "questions": {
            "questions": [
                {
                    "id": 1,
                    "type": "multiple_choice",
                    "question": "Apa kepanjangan dari WAN?",
                    "options": [
                        {
                            "id": "a",
                            "text": "Wide Area Network"
                        },
                        {
                            "id": "b",
                            "text": "Wireless Area Network"
                        },
                        {
                            "id": "c",
                            "text": "Web Area Network"
                        },
                        {
                            "id": "d",
                            "text": "World Area Network"
                        }
                    ],
                    "correct_answer": "a",
                    "explanation": "WAN adalah singkatan dari Wide Area Network."
                },
                {
                    "id": 2,
                    "type": "true_false",
                    "question": "FTP digunakan untuk mengirim email.",
                    "correct_answer": false,
                    "explanation": "FTP digunakan untuk mentransfer file, sedangkan SMTP digunakan untuk mengirim email."
                },
                {
                    "id": 3,
                    "type": "multiple_choice",
                    "question": "Berapa banyak lapisan dalam model OSI?",
                    "options": [
                        {
                            "id": "a",
                            "text": "4"
                        },
                        {
                            "id": "b",
                            "text": "5"
                        },
                        {
                            "id": "c",
                            "text": "6"
                        },
                        {
                            "id": "d",
                            "text": "7"
                        }
                    ],
                    "correct_answer": "d",
                    "explanation": "Model OSI memiliki 7 lapisan."
                },
                {
                    "id": 4,
                    "type": "multibox",
                    "question": "Manakah yang termasuk dalam layanan cloud computing?",
                    "options": [
                        {
                            "id": "a",
                            "text": "Penyimpanan data"
                        },
                        {
                            "id": "b",
                            "text": "Perangkat lunak sebagai layanan (SaaS)"
                        },
                        {
                            "id": "c",
                            "text": "Perangkat keras server"
                        },
                        {
                            "id": "d",
                            "text": "Platform sebagai layanan (PaaS)"
                        }
                    ],
                    "correct_answer": [
                        "a",
                        "b",
                        "d"
                    ],
                    "explanation": "Penyimpanan data, SaaS, dan PaaS adalah layanan cloud computing. Perangkat keras server bukan merupakan layanan cloud."
                },
                {
                    "id": 5,
                    "type": "multiple_choice",
                    "question": "Apa fungsi VPN?",
                    "options": [
                        {
                            "id": "a",
                            "text": "Mengirim email"
                        },
                        {
                            "id": "b",
                            "text": "Membuat koneksi aman melalui jaringan publik"
                        },
                        {
                            "id": "c",
                            "text": "Menerjemahkan nama domain"
                        },
                        {
                            "id": "d",
                            "text": "Mengakses situs web"
                        }
                    ],
                    "correct_answer": "b",
                    "explanation": "VPN membuat koneksi aman melalui jaringan publik."
                }
            ]
        }
    },
    {
        "context": "Protokol internet (IP) adalah seperangkat aturan yang mengatur format data yang dikirim melalui internet atau jaringan lokal.  IP mendefinisikan bagaimana komputer dan perangkat lain berkomunikasi satu sama lain.  Alamat IP adalah pengidentifikasi unik untuk setiap perangkat yang terhubung ke jaringan.  Ada dua versi utama IP: IPv4 dan IPv6.  IPv4 menggunakan alamat 32-bit, sedangkan IPv6 menggunakan alamat 128-bit.  Perbedaan utama lainnya adalah IPv6 memiliki ruang alamat yang jauh lebih besar daripada IPv4.  HTTP (Hypertext Transfer Protocol) adalah protokol yang digunakan untuk mentransfer data melalui World Wide Web.  Ketika Anda mengakses situs web, browser Anda mengirimkan permintaan HTTP ke server web, yang kemudian mengirimkan kembali halaman web yang diminta.  HTTPS (Hypertext Transfer Protocol Secure) adalah versi HTTP yang aman yang mengenkripsi komunikasi antara browser Anda dan server web, melindungi informasi sensitif dari akses yang tidak sah.  Server web adalah komputer yang menyimpan dan mengirimkan situs web.  Mereka menjalankan perangkat lunak server web, seperti Apache atau Nginx, yang menangani permintaan HTTP dari browser web.  Server web dapat menangani banyak permintaan secara bersamaan.  Load balancing mendistribusikan lalu lintas jaringan di beberapa server untuk meningkatkan kinerja dan ketersediaan.  DNS (Domain Name System) menerjemahkan nama domain yang mudah diingat (seperti google.com) ke alamat IP numerik yang digunakan oleh komputer. Keamanan jaringan sangat penting dalam dunia digital saat ini.  Firewall, sistem deteksi intrusi, dan perangkat lunak antivirus adalah alat penting untuk melindungi jaringan dari ancaman siber.  Serangan siber dapat berupa malware, phishing, denial-of-service attack, dan banyak lagi.  Penting untuk mengikuti praktik keamanan terbaik, seperti menggunakan kata sandi yang kuat, memperbarui perangkat lunak secara teratur, dan mendidik pengguna tentang ancaman siber. Jaringan komputer memungkinkan kita untuk berbagi sumber daya, seperti printer dan file, dan untuk berkomunikasi satu sama lain melalui email, pesan instan, dan video conference.  Topologi jaringan menggambarkan tata letak fisik atau logis dari jaringan.  Topologi umum termasuk bus, bintang, ring, dan mesh.  Ethernet adalah teknologi LAN yang paling umum digunakan.  Wi-Fi memungkinkan perangkat untuk terhubung ke jaringan tanpa kabel.  Switch jaringan menghubungkan beberapa perangkat di LAN, sedangkan router menghubungkan LAN ke internet.  Model OSI adalah kerangka kerja konseptual yang menstandardisasi komunikasi antar sistem komputer. Ini terdiri dari tujuh lapisan: fisik, tautan data, jaringan, transport, sesi, presentasi, dan aplikasi.  Setiap lapisan memiliki fungsi tertentu dalam proses komunikasi. Cloud computing menyediakan akses sesuai permintaan ke sumber daya komputasi bersama, seperti server, penyimpanan, dan perangkat lunak, melalui internet.  Layanan cloud umum termasuk penyimpanan data, perangkat lunak sebagai layanan (SaaS), dan platform sebagai layanan (PaaS).  Cloud computing menawarkan skalabilitas, fleksibilitas, dan penghematan biaya dibandingkan dengan solusi hosting tradisional.  Edge computing memproses data lebih dekat ke sumbernya, mengurangi latensi dan bandwidth yang dibutuhkan.  IoT (Internet of Things) menghubungkan perangkat sehari-hari ke internet, memungkinkan mereka untuk mengumpulkan dan bertukar data.  Smart home, kendaraan yang terhubung, dan perangkat yang dapat dikenakan adalah contoh aplikasi IoT.  Keamanan IoT merupakan pertimbangan penting, karena perangkat IoT yang terhubung dapat rentan terhadap serangan siber.   Big data mengacu pada kumpulan data yang terlalu besar dan kompleks untuk diproses oleh metode tradisional.  Data mining adalah proses mengekstrak pengetahuan yang berguna dari data dalam jumlah besar.  Kecerdasan buatan (AI) dan machine learning (ML) digunakan dalam jaringan komputer untuk mengotomatiskan tugas, meningkatkan kinerja, dan meningkatkan keamanan.  AI dan ML dapat digunakan untuk mendeteksi anomali, memprediksi kegagalan, dan mengoptimalkan lalu lintas jaringan. VPN (Virtual Private Network) menciptakan koneksi aman melalui jaringan publik, seperti internet, yang memungkinkan pengguna untuk mengakses sumber daya jaringan dengan aman dari lokasi terpencil.  Penggunaan VPN semakin populer karena meningkatnya kebutuhan akan keamanan dan privasi online.  TCP (Transmission Control Protocol) memastikan pengiriman data yang andal dengan memecah data menjadi paket-paket kecil dan melacak pengiriman setiap paket.  Jika paket hilang atau rusak, TCP akan meminta pengiriman ulang paket tersebut. 5G adalah standar jaringan seluler generasi kelima yang menawarkan kecepatan data yang jauh lebih tinggi dan latensi yang lebih rendah dibandingkan dengan generasi sebelumnya.  5G memungkinkan aplikasi baru, seperti augmented reality dan virtual reality, dan mendukung pertumbuhan IoT.  Kecerdasan buatan (AI) dan pembelajaran mesin (ML) digunakan dalam jaringan komputer untuk mengotomatiskan tugas, meningkatkan kinerja, dan meningkatkan keamanan.  AI dan ML dapat digunakan untuk mendeteksi anomali, memprediksi kegagalan, dan mengoptimalkan lalu lintas jaringan.",
        "questions": {
            "questions": [
                {
                    "id": 1,
                    "type": "multiple_choice",
                    "question": "Apa fungsi utama dari protokol IP?",
                    "options": [
                        {
                            "id": "a",
                            "text": "Mengirim email"
                        },
                        {
                            "id": "b",
                            "text": "Mengatur format data yang dikirim melalui jaringan"
                        },
                        {
                            "id": "c",
                            "text": "Menerjemahkan nama domain ke alamat IP"
                        },
                        {
                            "id": "d",
                            "text": "Mengenkripsi data"
                        }
                    ],
                    "correct_answer": "b",
                    "explanation": "Protokol IP mengatur format data yang dikirim melalui jaringan."
                },
                {
                    "id": 2,
                    "type": "true_false",
                    "question": "IPv4 menggunakan alamat 128-bit.",
                    "correct_answer": false,
                    "explanation": "IPv4 menggunakan alamat 32-bit, sedangkan IPv6 menggunakan alamat 128-bit."
                },
                {
                    "id": 3,
                    "type": "multiple_choice",
                    "question": "Apa yang dimaksud dengan HTTPS?",
                    "options": [
                        {
                            "id": "a",
                            "text": "Protokol untuk mentransfer file"
                        },
                        {
                            "id": "b",
                            "text": "Versi HTTP yang aman"
                        },
                        {
                            "id": "c",
                            "text": "Protokol untuk mengirim email"
                        },
                        {
                            "id": "d",
                            "text": "Topologi jaringan"
                        }
                    ],
                    "correct_answer": "b",
                    "explanation": "HTTPS adalah versi HTTP yang aman yang mengenkripsi komunikasi."
                },
                {
                    "id": 4,
                    "type": "multibox",
                    "question": "Manakah yang termasuk dalam contoh serangan siber?",
                    "options": [
                        {
                            "id": "a",
                            "text": "Malware"
                        },
                        {
                            "id": "b",
                            "text": "Phishing"
                        },
                        {
                            "id": "c",
                            "text": "Firewall"
                        },
                        {
                            "id": "d",
                            "text": "Denial-of-service attack"
                        }
                    ],
                    "correct_answer": [
                        "a",
                        "b",
                        "d"
                    ],
                    "explanation": "Malware, phishing, dan denial-of-service attack adalah contoh serangan siber. Firewall adalah sistem pertahanan."
                },
                {
                    "id": 5,
                    "type": "multiple_choice",
                    "question": "Apa fungsi load balancing pada server?",
                    "options": [
                        {
                            "id": "a",
                            "text": "Menyimpan data"
                        },
                        {
                            "id": "b",
                            "text": "Mendistribusikan lalu lintas jaringan"
                        },
                        {
                            "id": "c",
                            "text": "Menerjemahkan nama domain"
                        },
                        {
                            "id": "d",
                            "text": "Mengenali virus"
                        }
                    ],
                    "correct_answer": "b",
                    "explanation": "Load balancing mendistribusikan lalu lintas jaringan di beberapa server."
                }
            ]
        }
    },
    {
        "context": "Jaringan komputer, landasan dunia digital kita yang saling terhubung, memfasilitasi komunikasi dan kolaborasi tanpa batas melintasi batas geografis. Dari jaringan lokal kecil yang menghubungkan perangkat di rumah atau kantor hingga jaringan global luas yang mendukung internet, jaringan komputer telah merevolusi cara kita berinteraksi, bekerja, dan mengakses informasi. Protokol jaringan, seperti TCP/IP, HTTP, dan FTP, menetapkan aturan dan standar untuk transmisi data yang efisien dan andal. TCP/IP, khususnya, berfungsi sebagai tulang punggung internet, yang memungkinkan komunikasi yang mulus antara miliaran perangkat di seluruh dunia.  HTTP memfasilitasi akses ke situs web dan sumber daya online lainnya, sementara FTP memungkinkan transfer file yang efisien antar perangkat. Keamanan jaringan sangat penting untuk melindungi data dan sistem kita yang berharga dari ancaman siber yang terus berkembang. Firewall bertindak sebagai penjaga gerbang, mengontrol lalu lintas jaringan dan mencegah akses yang tidak sah. Sistem deteksi intrusi memantau aktivitas jaringan yang mencurigakan dan memberi tahu administrator tentang potensi pelanggaran. Perangkat lunak antivirus memindai file dan program untuk malware, melindungi perangkat dari infeksi.  Selain langkah-langkah ini, praktik keamanan yang baik, seperti menggunakan kata sandi yang kuat dan memperbarui perangkat lunak secara teratur, sangat penting untuk menjaga postur keamanan yang kuat.  Teknologi kriptografi memainkan peran penting dalam mengamankan komunikasi dan melindungi data sensitif. Algoritma enkripsi mengubah data menjadi bentuk yang tidak dapat dibaca, mencegah akses yang tidak sah selama transmisi atau penyimpanan. VPN (Virtual Private Networks) menawarkan lapisan keamanan tambahan dengan membuat koneksi aman melalui jaringan publik, seperti internet.  VPN mengenkripsi lalu lintas internet, melindunginya dari mata-mata dan memastikan privasi online. Cloud computing telah muncul sebagai model komputasi yang transformatif, menyediakan akses sesuai permintaan ke sumber daya komputasi bersama melalui internet. Layanan cloud, seperti penyimpanan data, perangkat lunak sebagai layanan (SaaS), dan platform sebagai layanan (PaaS), menawarkan skalabilitas, fleksibilitas, dan penghematan biaya dibandingkan dengan solusi hosting tradisional.  Edge computing, paradigma komputasi terdistribusi, membawa pemrosesan data lebih dekat ke sumbernya, mengurangi latensi dan bandwidth yang dibutuhkan.  IoT (Internet of Things), jaringan perangkat fisik yang saling terhubung, menghasilkan sejumlah besar data yang dapat dimanfaatkan untuk wawasan yang berharga.  Teknologi data mining memungkinkan ekstraksi pengetahuan dan pola yang bermakna dari kumpulan data yang besar ini. Kecerdasan buatan (AI) dan pembelajaran mesin (ML) semakin terintegrasi ke dalam jaringan komputer, yang memungkinkan otomatisasi tugas, peningkatan kinerja, dan langkah-langkah keamanan yang ditingkatkan. Algoritma AI dan ML dapat menganalisis lalu lintas jaringan, mendeteksi anomali, dan memprediksi potensi kegagalan, meningkatkan proaktif dan ketahanan jaringan. Server web memainkan peran penting dalam menyampaikan konten web kepada pengguna di seluruh dunia.  Mereka menyimpan file situs web dan memproses permintaan HTTP dari browser web, mengirimkan halaman web yang diminta ke pengguna. Load balancing mendistribusikan lalu lintas jaringan di beberapa server, memastikan kinerja dan ketersediaan yang optimal bahkan selama periode permintaan yang tinggi.  DNS (Domain Name System) menerjemahkan nama domain yang mudah dibaca manusia ke alamat IP numerik yang sesuai, memungkinkan perangkat untuk menemukan dan terhubung ke situs web dan server lain di internet.  Teknologi 5G, standar jaringan seluler generasi kelima, menawarkan kecepatan data yang jauh lebih cepat, latensi yang lebih rendah, dan peningkatan kapasitas dibandingkan dengan pendahulunya.  Kemajuan ini memungkinkan aplikasi baru dan inovatif di berbagai bidang, termasuk augmented reality, virtual reality, dan Internet of Things (IoT). Jaringan komputer telah menjadi tulang punggung masyarakat modern kita, memungkinkan kita untuk terhubung, berkomunikasi, dan mengakses informasi dengan cara yang belum pernah terjadi sebelumnya.  Evolusi jaringan yang berkelanjutan, didorong oleh inovasi teknologi seperti 5G, cloud computing, dan AI, menjanjikan untuk lebih meningkatkan kehidupan kita dan membuka kemungkinan baru untuk kolaborasi dan kemajuan.",
        "questions": {
            "questions": [
                {
                    "id": 1,
                    "type": "multiple_choice",
                    "question": "Apa fungsi utama dari protokol TCP/IP?",
                    "options": [
                        {
                            "id": "a",
                            "text": "Mengirim email"
                        },
                        {
                            "id": "b",
                            "text": "Mengakses situs web"
                        },
                        {
                            "id": "c",
                            "text": "Mentransfer file"
                        },
                        {
                            "id": "d",
                            "text": "Menjadi tulang punggung internet"
                        }
                    ],
                    "correct_answer": "d",
                    "explanation": "TCP/IP adalah protokol inti yang memungkinkan komunikasi antar perangkat di internet."
                },
                {
                    "id": 2,
                    "type": "true_false",
                    "question": "Firewall digunakan untuk mengenkripsi data.",
                    "correct_answer": false,
                    "explanation": "Firewall mengontrol lalu lintas jaringan, bukan mengenkripsi data. Kriptografi yang digunakan untuk mengenkripsi data."
                },
                {
                    "id": 3,
                    "type": "multiple_choice",
                    "question": "Apa yang dimaksud dengan cloud computing?",
                    "options": [
                        {
                            "id": "a",
                            "text": "Jaringan lokal kecil"
                        },
                        {
                            "id": "b",
                            "text": "Akses sesuai permintaan ke sumber daya komputasi bersama"
                        },
                        {
                            "id": "c",
                            "text": "Perangkat keras untuk menyimpan data"
                        },
                        {
                            "id": "d",
                            "text": "Perangkat lunak untuk mengakses internet"
                        }
                    ],
                    "correct_answer": "b",
                    "explanation": "Cloud computing menyediakan akses ke sumber daya komputasi melalui internet."
                },
                {
                    "id": 4,
                    "type": "multibox",
                    "question": "Manakah yang termasuk dalam praktik keamanan jaringan yang baik?",
                    "options": [
                        {
                            "id": "a",
                            "text": "Menggunakan kata sandi yang kuat"
                        },
                        {
                            "id": "b",
                            "text": "Memperbarui perangkat lunak secara teratur"
                        },
                        {
                            "id": "c",
                            "text": "Menggunakan software bajakan"
                        },
                        {
                            "id": "d",
                            "text": "Mengklik tautan yang mencurigakan"
                        }
                    ],
                    "correct_answer": [
                        "a",
                        "b"
                    ],
                    "explanation": "Kata sandi yang kuat dan pembaruan perangkat lunak berkontribusi pada keamanan jaringan. Software bajakan dan tautan mencurigakan justru berbahaya."
                },
                {
                    "id": 5,
                    "type": "multiple_choice",
                    "question": "Apa fungsi load balancing?",
                    "options": [
                        {
                            "id": "a",
                            "text": "Mengirim email"
                        },
                        {
                            "id": "b",
                            "text": "Mendistribusikan lalu lintas jaringan di beberapa server"
                        },
                        {
                            "id": "c",
                            "text": "Menerjemahkan nama domain"
                        },
                        {
                            "id": "d",
                            "text": "Mengenali virus"
                        }
                    ],
                    "correct_answer": "b",
                    "explanation": "Load balancing mendistribusikan lalu lintas untuk meningkatkan kinerja dan ketersediaan."
                }
            ]
        }
    },
    {
        "context": "Jaringan komputer membentuk dasar dari internet, menghubungkan miliaran perangkat di seluruh dunia dan memungkinkan komunikasi dan pertukaran informasi yang belum pernah terjadi sebelumnya.  Jaringan ini, mulai dari jaringan rumah kecil hingga jaringan perusahaan besar, mengandalkan protokol, perangkat keras, dan perangkat lunak khusus untuk berfungsi secara efektif dan aman. Protokol jaringan seperti TCP/IP, fondasi internet, menentukan aturan untuk transmisi data yang andal.  TCP memastikan integritas data dengan mengelola aliran paket data, sementara IP menangani pengalamatan dan routing data antar jaringan.  Protokol lain, seperti HTTP dan HTTPS, mengatur komunikasi antara browser web dan server web, memungkinkan akses ke situs web dan sumber daya online.  HTTPS, khususnya, mengenkripsi komunikasi untuk melindungi data sensitif selama transmisi. Keamanan jaringan adalah hal yang sangat penting untuk melindungi sistem dan data dari ancaman siber yang terus berkembang. Firewall bertindak sebagai garis pertahanan pertama, memfilter lalu lintas jaringan dan memblokir akses yang tidak sah.  Sistem deteksi intrusi (IDS) memantau aktivitas jaringan untuk perilaku yang mencurigakan, memberi tahu administrator tentang potensi pelanggaran.  Perangkat lunak antivirus memindai file dan aplikasi untuk malware, membantu mencegah dan mengurangi infeksi.  Praktik keamanan yang baik, seperti menggunakan kata sandi yang kuat, menerapkan autentikasi multi-faktor, dan menjaga perangkat lunak tetap mutakhir, sangat penting untuk menjaga postur keamanan yang kuat. Kriptografi memainkan peran penting dalam mengamankan komunikasi dan melindungi data sensitif.  Algoritma kriptografi yang kuat mengenkripsi data, menjadikannya tidak dapat dibaca oleh pihak yang tidak berwenang.  VPN (Virtual Private Networks) memperluas keamanan ini dengan membuat koneksi terenkripsi melalui jaringan publik seperti internet, melindungi data yang dikirim dan diterima. Cloud computing telah mengubah lanskap TI dengan menyediakan akses sesuai permintaan ke sumber daya komputasi bersama melalui internet.  Layanan cloud, termasuk penyimpanan data, perangkat lunak sebagai layanan (SaaS), dan platform sebagai layanan (PaaS), menawarkan skalabilitas, fleksibilitas, dan penghematan biaya.  Organisasi dapat memanfaatkan sumber daya cloud untuk memenuhi kebutuhan komputasi mereka tanpa investasi besar dalam infrastruktur fisik.  Edge computing melengkapi cloud computing dengan memproses data lebih dekat ke sumbernya, mengurangi latensi dan bandwidth yang dibutuhkan. Internet of Things (IoT), jaringan perangkat fisik yang terhubung ke internet, menghasilkan data dalam jumlah besar yang dapat dimanfaatkan untuk wawasan yang berharga.  Data mining memungkinkan ekstraksi pengetahuan dan pola dari kumpulan data yang besar ini.  Kecerdasan buatan (AI) dan pembelajaran mesin (ML) semakin diintegrasikan ke dalam jaringan untuk mengotomatiskan tugas, meningkatkan kinerja, dan meningkatkan keamanan.  Algoritma AI dan ML dapat menganalisis lalu lintas jaringan, mendeteksi anomali, dan meningkatkan respons terhadap ancaman. Server web adalah pusat dari World Wide Web, yang menyimpan dan mengirimkan situs web ke pengguna di seluruh dunia.  Mereka memproses permintaan HTTP dari browser web, mengirimkan halaman web yang diminta.  Load balancing mendistribusikan lalu lintas di beberapa server, memastikan kinerja dan ketersediaan yang optimal.  DNS (Domain Name System) bertindak sebagai buku telepon internet, menerjemahkan nama domain yang ramah pengguna ke alamat IP numerik yang digunakan komputer untuk menemukan satu sama lain.  Perkembangan teknologi web seperti HTML5, CSS3, dan JavaScript telah memperkaya pengalaman menjelajah web, memungkinkan situs web yang interaktif dan dinamis.  Teknologi 5G, standar jaringan seluler terbaru, menjanjikan kecepatan data yang lebih cepat, latensi yang lebih rendah, dan peningkatan bandwidth, membuka jalan bagi aplikasi baru dan inovatif. Jaringan komputer telah merevolusi cara kita hidup, bekerja, dan berinteraksi satu sama lain.  Dari email dan media sosial hingga e-commerce dan pendidikan online, jaringan telah menjadi bagian tak terpisahkan dari kehidupan kita sehari-hari.  Seiring kemajuan teknologi, jaringan komputer akan terus berkembang, menghubungkan kita dengan cara yang lebih inovatif dan bermakna.",
        "questions": {
            "questions": [
                {
                    "id": 1,
                    "type": "multiple_choice",
                    "question": "Protokol apa yang bertanggung jawab untuk mengatur komunikasi antara browser web dan server web?",
                    "options": [
                        {
                            "id": "a",
                            "text": "TCP/IP"
                        },
                        {
                            "id": "b",
                            "text": "HTTP/HTTPS"
                        },
                        {
                            "id": "c",
                            "text": "FTP"
                        },
                        {
                            "id": "d",
                            "text": "SMTP"
                        }
                    ],
                    "correct_answer": "b",
                    "explanation": "HTTP dan HTTPS digunakan untuk komunikasi antara browser dan server web."
                },
                {
                    "id": 2,
                    "type": "true_false",
                    "question": "Sistem deteksi intrusi (IDS) mengenkripsi data untuk melindunginya dari akses yang tidak sah.",
                    "correct_answer": false,
                    "explanation": "IDS memantau aktivitas jaringan untuk perilaku yang mencurigakan, bukan mengenkripsi data. Enkripsi adalah fungsi dari kriptografi."
                },
                {
                    "id": 3,
                    "type": "multiple_choice",
                    "question": "Apa manfaat utama dari cloud computing?",
                    "options": [
                        {
                            "id": "a",
                            "text": "Meningkatkan kecepatan internet"
                        },
                        {
                            "id": "b",
                            "text": "Menyediakan akses ke sumber daya komputasi sesuai permintaan"
                        },
                        {
                            "id": "c",
                            "text": "Melindungi dari serangan siber"
                        },
                        {
                            "id": "d",
                            "text": "Menerjemahkan nama domain ke alamat IP"
                        }
                    ],
                    "correct_answer": "b",
                    "explanation": "Cloud computing menawarkan akses sesuai permintaan ke sumber daya seperti server, penyimpanan, dan perangkat lunak."
                },
                {
                    "id": 4,
                    "type": "multibox",
                    "question": "Manakah yang merupakan komponen penting dari keamanan jaringan?",
                    "options": [
                        {
                            "id": "a",
                            "text": "Firewall"
                        },
                        {
                            "id": "b",
                            "text": "Sistem deteksi intrusi"
                        },
                        {
                            "id": "c",
                            "text": "Perangkat lunak antivirus"
                        },
                        {
                            "id": "d",
                            "text": "Kata sandi yang lemah"
                        }
                    ],
                    "correct_answer": [
                        "a",
                        "b",
                        "c"
                    ],
                    "explanation": "Firewall, IDS, dan perangkat lunak antivirus adalah komponen penting keamanan jaringan. Kata sandi yang lemah adalah praktik yang buruk."
                },
                {
                    "id": 5,
                    "type": "multiple_choice",
                    "question": "Apa fungsi DNS?",
                    "options": [
                        {
                            "id": "a",
                            "text": "Mengirim email"
                        },
                        {
                            "id": "b",
                            "text": "Mentransfer file"
                        },
                        {
                            "id": "c",
                            "text": "Menerjemahkan nama domain ke alamat IP"
                        },
                        {
                            "id": "d",
                            "text": "Mengenkripsi data"
                        }
                    ],
                    "correct_answer": "c",
                    "explanation": "DNS menerjemahkan nama domain yang mudah diingat ke alamat IP numerik."
                }
            ]
        }
    },
    {
        "context": "Jaringan komputer, sistem yang saling terhubung yang memungkinkan perangkat untuk berkomunikasi dan berbagi sumber daya, telah menjadi bagian tak terpisahkan dari dunia modern kita. Dari jaringan rumah kecil yang menghubungkan komputer dan printer hingga internet global yang luas, jaringan memfasilitasi pertukaran informasi dan mendukung berbagai layanan penting. Protokol jaringan, seperti TCP/IP, HTTP, dan FTP, menyediakan kerangka kerja untuk komunikasi data yang efisien dan terstruktur. TCP/IP, suite protokol inti internet, memastikan transmisi data yang andal melalui jaringan.  HTTP memungkinkan akses ke situs web dan sumber daya online lainnya, sedangkan FTP memfasilitasi transfer file antar perangkat. Keamanan jaringan sangat penting untuk melindungi sistem dan data dari ancaman siber yang terus berkembang.  Firewall bertindak sebagai penjaga gerbang, mengontrol lalu lintas jaringan masuk dan keluar dan memblokir akses yang tidak sah.  Sistem deteksi intrusi (IDS) memantau aktivitas jaringan untuk perilaku yang mencurigakan, memberi tahu administrator tentang potensi pelanggaran keamanan.  Perangkat lunak antivirus memindai file dan program untuk malware, membantu mencegah dan memitigasi infeksi.  Selain itu, praktik keamanan yang baik, seperti menggunakan kata sandi yang kuat dan memperbarui perangkat lunak secara teratur, sangat penting untuk menjaga postur keamanan yang kuat. Kriptografi memainkan peran penting dalam mengamankan komunikasi dan melindungi data sensitif.  Algoritma enkripsi mengubah data menjadi bentuk yang tidak dapat dibaca, mencegah akses yang tidak sah selama transmisi atau penyimpanan.  VPN (Virtual Private Networks) membuat koneksi aman melalui jaringan publik seperti internet, melindungi data dari intersepsi dan memastikan privasi online. Cloud computing telah merevolusi cara individu dan organisasi mengakses dan menggunakan sumber daya komputasi.  Layanan cloud, termasuk penyimpanan data, perangkat lunak sebagai layanan (SaaS), dan platform sebagai layanan (PaaS), menyediakan akses sesuai permintaan ke sumber daya komputasi bersama melalui internet.  Model komputasi berbasis cloud ini menawarkan skalabilitas, fleksibilitas, dan penghematan biaya dibandingkan dengan solusi hosting tradisional.  Edge computing, paradigma komputasi terdistribusi, membawa pemrosesan data lebih dekat ke sumbernya, mengurangi latensi dan kebutuhan bandwidth. Internet of Things (IoT), jaringan perangkat fisik yang terhubung ke internet, menghasilkan sejumlah besar data yang dapat dimanfaatkan untuk mendapatkan wawasan yang berharga. Data mining memungkinkan ekstraksi pengetahuan dan pola yang bermakna dari kumpulan data yang besar ini.  Kecerdasan buatan (AI) dan pembelajaran mesin (ML) semakin terintegrasi ke dalam jaringan komputer untuk mengotomatiskan tugas, meningkatkan kinerja, dan meningkatkan keamanan.  Algoritma AI dan ML dapat menganalisis lalu lintas jaringan, mendeteksi anomali, dan meningkatkan respons ancaman siber.Server web memainkan peran penting dalam menyampaikan konten web kepada pengguna di seluruh dunia.  Mereka menyimpan file situs web dan memproses permintaan HTTP dari browser web, mengirimkan halaman web yang diminta ke pengguna.  Load balancing mendistribusikan lalu lintas jaringan di beberapa server, memastikan kinerja dan ketersediaan yang optimal, terutama selama periode permintaan puncak.  DNS (Domain Name System) bertindak sebagai buku telepon internet, menerjemahkan nama domain yang mudah diingat ke alamat IP numerik yang digunakan komputer untuk menemukan satu sama lain.  Perkembangan teknologi web seperti HTML5, CSS3, dan JavaScript telah memperkaya pengalaman menjelajah web, memungkinkan pembuatan situs web yang interaktif dan dinamis.  Teknologi 5G, standar jaringan seluler terbaru, menawarkan kecepatan data yang secara signifikan lebih cepat, latensi yang lebih rendah, dan peningkatan bandwidth, membuka jalan bagi aplikasi baru dan inovatif. Jaringan komputer telah mengubah secara mendasar cara kita hidup, bekerja, dan berinteraksi satu sama lain.  Dari email dan media sosial hingga e-commerce dan pendidikan online, jaringan telah menjadi bagian tak terpisahkan dari kehidupan kita sehari-hari.  Saat teknologi terus berkembang, jaringan komputer akan terus berkembang, menghubungkan kita dengan cara yang lebih inovatif dan bermakna. Model OSI (Open Systems Interconnection), kerangka kerja konseptual, menstandardisasi komunikasi antar sistem komputer dengan membaginya menjadi tujuh lapisan: fisik, tautan data, jaringan, transport, sesi, presentasi, dan aplikasi.  Setiap lapisan memiliki fungsi tertentu dalam proses komunikasi, memastikan interoperabilitas antara vendor dan teknologi yang berbeda.",
        "questions": {
            "questions": [
                {
                    "id": 1,
                    "type": "multiple_choice",
                    "question": "Apa fungsi utama protokol TCP dalam TCP/IP?",
                    "options": [
                        {
                            "id": "a",
                            "text": "Mengirim email"
                        },
                        {
                            "id": "b",
                            "text": "Mengakses situs web"
                        },
                        {
                            "id": "c",
                            "text": "Memastikan pengiriman data yang andal"
                        },
                        {
                            "id": "d",
                            "text": "Menerjemahkan nama domain"
                        }
                    ],
                    "correct_answer": "c",
                    "explanation": "TCP bertanggung jawab atas pengiriman data yang andal di internet."
                },
                {
                    "id": 2,
                    "type": "true_false",
                    "question": "VPN digunakan untuk mengenkripsi lalu lintas internet dan meningkatkan privasi online.",
                    "correct_answer": true,
                    "explanation": "VPN mengenkripsi data dan menyembunyikan alamat IP, meningkatkan privasi."
                },
                {
                    "id": 3,
                    "type": "multiple_choice",
                    "question": "Apa yang dimaksud dengan edge computing?",
                    "options": [
                        {
                            "id": "a",
                            "text": "Memproses data di cloud"
                        },
                        {
                            "id": "b",
                            "text": "Memproses data lebih dekat ke sumbernya"
                        },
                        {
                            "id": "c",
                            "text": "Menyimpan data di server terpusat"
                        },
                        {
                            "id": "d",
                            "text": "Mentransfer file antar perangkat"
                        }
                    ],
                    "correct_answer": "b",
                    "explanation": "Edge computing memproses data di dekat sumber, bukan di cloud atau server terpusat."
                },
                {
                    "id": 4,
                    "type": "multibox",
                    "question": "Manakah yang merupakan manfaat dari cloud computing?",
                    "options": [
                        {
                            "id": "a",
                            "text": "Skalabilitas"
                        },
                        {
                            "id": "b",
                            "text": "Fleksibilitas"
                        },
                        {
                            "id": "c",
                            "text": "Keamanan yang lebih rendah"
                        },
                        {
                            "id": "d",
                            "text": "Penghematan biaya"
                        }
                    ],
                    "correct_answer": [
                        "a",
                        "b",
                        "d"
                    ],
                    "explanation": "Cloud computing menawarkan skalabilitas, fleksibilitas, dan penghematan biaya. Keamanan yang lebih rendah bukanlah manfaat."
                },
                {
                    "id": 5,
                    "type": "multiple_choice",
                    "question": "Apa fungsi load balancing pada server web?",
                    "options": [
                        {
                            "id": "a",
                            "text": "Menyimpan file situs web"
                        },
                        {
                            "id": "b",
                            "text": "Menerjemahkan nama domain ke alamat IP"
                        },
                        {
                            "id": "c",
                            "text": "Mendistribusikan lalu lintas jaringan di beberapa server"
                        },
                        {
                            "id": "d",
                            "text": "Mengenali virus"
                        }
                    ],
                    "correct_answer": "c",
                    "explanation": "Load balancing mendistribusikan lalu lintas untuk meningkatkan kinerja dan mencegah kelebihan beban pada satu server."
                }
            ]
        }
    },
    {
        "context": "Jaringan komputer, sistem saraf dunia digital, menghubungkan miliaran perangkat dan memungkinkan komunikasi dan kolaborasi yang belum pernah terjadi sebelumnya di seluruh dunia. Dari jaringan rumah kecil yang menghubungkan komputer pribadi dan printer hingga jaringan perusahaan besar yang mendukung operasi global, jaringan komputer telah merevolusi cara kita hidup, bekerja, dan berinteraksi. Protokol jaringan, seperangkat aturan yang mengatur komunikasi data, sangat penting untuk berfungsinya jaringan ini. TCP/IP, suite protokol inti internet, menyediakan mekanisme yang andal untuk transmisi data antar perangkat. TCP (Transmission Control Protocol) memastikan pengiriman data yang andal dengan menetapkan koneksi dan mengelola aliran paket data, sementara IP (Internet Protocol) menangani pengalamatan dan perutean data melalui jaringan. Protokol lain, seperti HTTP (Hypertext Transfer Protocol) dan HTTPS, memfasilitasi akses ke situs web dan sumber daya online. HTTPS, dengan kemampuan enkripsinya, melindungi data sensitif selama transmisi, menjaga keamanan dan privasi. Keamanan jaringan sangat penting di lanskap digital saat ini. Firewall bertindak sebagai garis pertahanan pertama, memfilter lalu lintas jaringan dan memblokir akses yang tidak sah. Sistem deteksi intrusi (IDS) memantau aktivitas jaringan secara real time, mencari pola dan anomali yang mencurigakan yang dapat mengindikasikan serangan siber.  Perangkat lunak antivirus memindai file dan aplikasi untuk malware, membantu mencegah dan mengurangi infeksi.  Praktik keamanan yang baik, seperti menggunakan kata sandi yang kuat, menerapkan autentikasi multi-faktor, dan menjaga perangkat lunak tetap mutakhir, sangat penting untuk mempertahankan postur keamanan yang kuat. Teknologi kriptografi memainkan peran penting dalam mengamankan komunikasi dan melindungi data sensitif dari akses yang tidak sah. Algoritma enkripsi mengubah data menjadi bentuk yang tidak dapat dibaca, menjadikannya tidak dapat dipahami oleh pihak yang tidak berwenang. VPN (Virtual Private Networks) menawarkan lapisan keamanan tambahan dengan membuat koneksi terenkripsi melalui jaringan publik, seperti internet. VPN mengenkripsi lalu lintas internet, melindunginya dari mata-mata dan memastikan privasi online. Cloud computing telah muncul sebagai model komputasi yang transformatif, menyediakan akses sesuai permintaan ke sumber daya komputasi bersama melalui internet. Layanan cloud, seperti penyimpanan data, perangkat lunak sebagai layanan (SaaS), dan platform sebagai layanan (PaaS), menawarkan skalabilitas, fleksibilitas, dan penghematan biaya dibandingkan dengan infrastruktur TI tradisional.  Edge computing, paradigma komputasi terdistribusi, membawa pemrosesan data lebih dekat ke sumbernya, mengurangi latensi dan kebutuhan bandwidth.  Edge computing sangat berguna untuk aplikasi yang peka terhadap waktu, seperti kendaraan otonom dan kota pintar. Internet of Things (IoT), jaringan perangkat fisik yang saling terhubung, menghasilkan data dalam jumlah besar yang dapat dimanfaatkan untuk mendapatkan wawasan yang berharga.  Data mining, proses ekstraksi pengetahuan dari kumpulan data yang besar, memungkinkan bisnis dan organisasi untuk mengidentifikasi tren, pola, dan anomali. Kecerdasan buatan (AI) dan pembelajaran mesin (ML) semakin terintegrasi ke dalam jaringan komputer untuk mengotomatiskan tugas, meningkatkan kinerja, dan meningkatkan keamanan.  Algoritma AI dan ML dapat menganalisis lalu lintas jaringan, mendeteksi anomali, dan memprediksi potensi kegagalan. Server web, komponen inti dari infrastruktur internet, menyimpan dan mengirimkan situs web kepada pengguna di seluruh dunia.  Mereka memproses permintaan HTTP dari browser web, mengirimkan kembali halaman web yang diminta.  Load balancing mendistribusikan lalu lintas jaringan di beberapa server, memastikan kinerja dan ketersediaan yang optimal bahkan selama periode permintaan yang tinggi.  DNS (Domain Name System) menerjemahkan nama domain yang mudah diingat ke alamat IP numerik, memungkinkan pengguna untuk mengakses situs web tanpa harus mengingat alamat IP yang kompleks.  Perkembangan teknologi web, seperti HTML5, CSS3, dan JavaScript, telah menyebabkan pengalaman web yang lebih interaktif dan dinamis.  Teknologi 5G menjanjikan kecepatan data yang lebih cepat, latensi yang lebih rendah, dan peningkatan bandwidth, membuka jalan bagi berbagai aplikasi dan layanan baru. Jaringan komputer telah menjadi sangat diperlukan untuk cara kita hidup, bekerja, dan berkomunikasi.  Dari email dan media sosial hingga e-commerce dan pendidikan online, jaringan telah mengubah interaksi kita dan memungkinkan kolaborasi global.  Seiring kemajuan teknologi, jaringan komputer akan terus berkembang, membentuk masa depan dunia digital kita yang saling terhubung.",
        "questions": {
            "questions": [
                {
                    "id": 1,
                    "type": "multiple_choice",
                    "question": "Apa fungsi utama protokol IP dalam TCP/IP?",
                    "options": [
                        {
                            "id": "a",
                            "text": "Mengirim email"
                        },
                        {
                            "id": "b",
                            "text": "Mengakses situs web"
                        },
                        {
                            "id": "c",
                            "text": "Mentransfer file"
                        },
                        {
                            "id": "d",
                            "text": "Pengalamatan dan perutean data"
                        }
                    ],
                    "correct_answer": "d",
                    "explanation": "IP menangani pengalamatan dan perutean data dalam jaringan."
                },
                {
                    "id": 2,
                    "type": "true_false",
                    "question": "HTTP menyediakan komunikasi yang terenkripsi untuk melindungi data sensitif.",
                    "correct_answer": false,
                    "explanation": "HTTPS, bukan HTTP, yang menyediakan enkripsi untuk keamanan."
                },
                {
                    "id": 3,
                    "type": "multiple_choice",
                    "question": "Apa yang dimaksud dengan edge computing?",
                    "options": [
                        {
                            "id": "a",
                            "text": "Memproses data di cloud"
                        },
                        {
                            "id": "b",
                            "text": "Memproses data lebih dekat ke sumbernya"
                        },
                        {
                            "id": "c",
                            "text": "Menyimpan data di server terpusat"
                        },
                        {
                            "id": "d",
                            "text": "Mentransfer file antar perangkat"
                        }
                    ],
                    "correct_answer": "b",
                    "explanation": "Edge computing memproses data di dekat sumbernya untuk mengurangi latensi."
                },
                {
                    "id": 4,
                    "type": "multibox",
                    "question": "Manakah yang merupakan manfaat dari cloud computing?",
                    "options": [
                        {
                            "id": "a",
                            "text": "Skalabilitas"
                        },
                        {
                            "id": "b",
                            "text": "Fleksibilitas"
                        },
                        {
                            "id": "c",
                            "text": "Keamanan yang lebih rendah"
                        },
                        {
                            "id": "d",
                            "text": "Penghematan biaya"
                        }
                    ],
                    "correct_answer": [
                        "a",
                        "b",
                        "d"
                    ],
                    "explanation": "Cloud computing menawarkan skalabilitas, fleksibilitas, dan penghematan biaya."
                },
                {
                    "id": "5",
                    "type": "multiple_choice",
                    "question": "Apa fungsi load balancing pada server web?",
                    "options": [
                        {
                            "id": "a",
                            "text": "Menyimpan file situs web"
                        },
                        {
                            "id": "b",
                            "text": "Menerjemahkan nama domain ke alamat IP"
                        },
                        {
                            "id": "c",
                            "text": "Mendistribusikan lalu lintas jaringan di beberapa server"
                        },
                        {
                            "id": "d",
                            "text": "Mengenali virus"
                        }
                    ],
                    "correct_answer": "c",
                    "explanation": "Load balancing mendistribusikan lalu lintas untuk kinerja dan ketersediaan."
                }
            ]
        }
    },
    {
        "context": "Jaringan komputer, tulang punggung infrastruktur digital kita, telah merevolusi cara kita berkomunikasi, berkolaborasi, dan mengakses informasi. Jaringan ini, mulai dari jaringan rumah kecil hingga internet global yang luas, memungkinkan perangkat untuk terhubung dan berbagi data dengan kecepatan dan efisiensi yang belum pernah terjadi sebelumnya. Protokol jaringan, seperangkat aturan yang mengatur transmisi data, sangat penting untuk berfungsinya jaringan ini.  TCP/IP, suite protokol yang mendasari internet, memungkinkan komunikasi yang andal dan efisien antara miliaran perangkat di seluruh dunia. TCP (Transmission Control Protocol) memastikan pengiriman data yang andal, sementara IP (Internet Protocol) menangani pengalamatan dan perutean data melalui jaringan yang kompleks.  Protokol lain, seperti HTTP (Hypertext Transfer Protocol) dan HTTPS, memungkinkan akses ke situs web dan sumber daya web.  HTTPS mengenkripsi komunikasi, melindungi data sensitif dari akses yang tidak sah. Keamanan jaringan sangat penting di dunia digital saat ini.  Firewall bertindak sebagai penjaga gerbang, mengontrol lalu lintas jaringan masuk dan keluar dan mencegah akses yang tidak sah.  Sistem deteksi intrusi (IDS) memantau aktivitas jaringan untuk perilaku yang mencurigakan, mengingatkan administrator tentang potensi pelanggaran.  Perangkat lunak antivirus memindai file dan aplikasi untuk malware, membantu mencegah dan memitigasi infeksi.  Praktik keamanan yang baik, seperti menggunakan kata sandi yang kuat, menerapkan autentikasi multi-faktor, dan menjaga perangkat lunak tetap mutakhir, sangat penting untuk postur keamanan yang kuat. Kriptografi memainkan peran penting dalam mengamankan komunikasi dan melindungi data sensitif dari intersepsi.  Algoritma kriptografi yang canggih mengenkripsi data, menjadikannya tidak dapat dibaca oleh pihak yang tidak berwenang. VPN (Virtual Private Networks) membuat koneksi aman melalui jaringan publik, seperti internet, memberikan privasi dan keamanan tambahan untuk data yang dikirimkan. Cloud computing telah mengubah lanskap IT dengan menyediakan akses sesuai permintaan ke sumber daya komputasi bersama melalui internet.  Layanan cloud, seperti penyimpanan data, perangkat lunak sebagai layanan (SaaS), dan platform sebagai layanan (PaaS), menawarkan skalabilitas, fleksibilitas, dan penghematan biaya dibandingkan dengan infrastruktur TI tradisional.  Edge computing melengkapi cloud computing dengan memproses data lebih dekat ke sumbernya, mengurangi latensi dan kebutuhan bandwidth.  Ini sangat bermanfaat untuk aplikasi yang memerlukan respons waktu nyata, seperti kendaraan otonom dan Internet of Things (IoT).  IoT, jaringan perangkat fisik yang terhubung ke internet, menghasilkan sejumlah besar data yang dapat dianalisis untuk wawasan yang berharga. Data mining memungkinkan ekstraksi pengetahuan dan pola dari kumpulan data yang besar ini, mendorong pengambilan keputusan berdasarkan data.  Kecerdasan buatan (AI) dan pembelajaran mesin (ML) semakin diintegrasikan ke dalam jaringan komputer untuk mengotomatiskan tugas, meningkatkan kinerja, dan meningkatkan keamanan.  Algoritma AI dan ML dapat menganalisis lalu lintas jaringan, mendeteksi anomali, dan memprediksi potensi kegagalan, memungkinkan tindakan proaktif dan pengoptimalan sumber daya. Server web memainkan peran penting dalam mendistribusikan konten web ke pengguna di seluruh dunia.  Mereka menyimpan file situs web dan memproses permintaan HTTP dari browser web, mengirimkan kembali halaman web yang diminta.  Load balancing mendistribusikan lalu lintas jaringan di beberapa server, memastikan kinerja dan ketersediaan yang optimal, terutama selama periode permintaan yang tinggi.  DNS (Domain Name System) menerjemahkan nama domain yang mudah dibaca manusia ke alamat IP numerik yang sesuai, memungkinkan pengguna untuk mengakses situs web tanpa harus mengingat alamat IP.  Perkembangan teknologi web, seperti HTML5, CSS3, dan JavaScript, telah memperkaya pengalaman menjelajah web, memungkinkan situs web yang interaktif dan dinamis.  Teknologi 5G, standar jaringan seluler generasi kelima, menawarkan kecepatan data yang signifikan lebih cepat, latensi yang lebih rendah, dan peningkatan bandwidth, membuka kemungkinan baru untuk aplikasi dan layanan. Jaringan komputer telah mengubah secara mendasar cara kita hidup, bekerja, dan berinteraksi.  Dari email dan media sosial hingga e-commerce dan pendidikan online, jaringan telah menjadi bagian tak terpisahkan dari kehidupan kita sehari-hari.  Seiring kemajuan teknologi, jaringan komputer akan terus berkembang, membentuk masa depan komunikasi dan kolaborasi digital.",
        "questions": {
            "questions": [
                {
                    "id": 1,
                    "type": "multiple_choice",
                    "question": "Apa fungsi utama dari protokol IP?",
                    "options": [
                        {
                            "id": "a",
                            "text": "Memastikan pengiriman data yang andal"
                        },
                        {
                            "id": "b",
                            "text": "Mengenkripsi data untuk keamanan"
                        },
                        {
                            "id": "c",
                            "text": "Pengalamatan dan perutean data"
                        },
                        {
                            "id": "d",
                            "text": "Mengakses situs web"
                        }
                    ],
                    "correct_answer": "c",
                    "explanation": "IP bertanggung jawab atas pengalamatan dan perutean data dalam jaringan."
                },
                {
                    "id": 2,
                    "type": "true_false",
                    "question": "HTTPS adalah versi HTTP yang aman yang mengenkripsi komunikasi.",
                    "correct_answer": true,
                    "explanation": "HTTPS mengenkripsi data untuk keamanan."
                },
                {
                    "id": 3,
                    "type": "multiple_choice",
                    "question": "Apa manfaat dari edge computing?",
                    "options": [
                        {
                            "id": "a",
                            "text": "Mengurangi latensi"
                        },
                        {
                            "id": "b",
                            "text": "Meningkatkan kebutuhan bandwidth"
                        },
                        {
                            "id": "c",
                            "text": "Memproses data di cloud"
                        },
                        {
                            "id": "d",
                            "text": "Menyimpan data di server terpusat"
                        }
                    ],
                    "correct_answer": "a",
                    "explanation": "Edge computing mengurangi latensi dengan memproses data lebih dekat ke sumbernya."
                },
                {
                    "id": 4,
                    "type": "multibox",
                    "question": "Manakah yang merupakan komponen penting dari keamanan jaringan?",
                    "options": [
                        {
                            "id": "a",
                            "text": "Firewall"
                        },
                        {
                            "id": "b",
                            "text": "Sistem deteksi intrusi (IDS)"
                        },
                        {
                            "id": "c",
                            "text": "Perangkat lunak antivirus"
                        },
                        {
                            "id": "d",
                            "text": "Kata sandi yang lemah"
                        }
                    ],
                    "correct_answer": [
                        "a",
                        "b",
                        "c"
                    ],
                    "explanation": "Firewall, IDS, dan antivirus adalah alat keamanan penting. Kata sandi yang lemah adalah praktik yang buruk."
                },
                {
                    "id": 5,
                    "type": "multiple_choice",
                    "question": "Apa fungsi load balancing pada server web?",
                    "options": [
                        {
                            "id": "a",
                            "text": "Menyimpan file situs web"
                        },
                        {
                            "id": "b",
                            "text": "Menerjemahkan nama domain ke alamat IP"
                        },
                        {
                            "id": "c",
                            "text": "Mendistribusikan lalu lintas jaringan di beberapa server"
                        },
                        {
                            "id": "d",
                            "text": "Mengenali virus"
                        }
                    ],
                    "correct_answer": "c",
                    "explanation": "Load balancing mendistribusikan lalu lintas untuk kinerja dan ketersediaan."
                }
            ]
        }
    }
]